[{"question_id": 34602, "answer": "dakota digital"}, {"question_id": 34603, "answer": "copenhagen"}, {"question_id": 34604, "answer": "ale"}, {"question_id": 34605, "answer": "bowmore"}, {"question_id": 34606, "answer": "10 years"}, {"question_id": 34607, "answer": "22"}, {"question_id": 34608, "answer": "10:10"}, {"question_id": 34609, "answer": "ap"}, {"question_id": 34610, "answer": "alex murta"}, {"question_id": 34611, "answer": "philippe molitor"}, {"question_id": 34612, "answer": "off"}, {"question_id": 34613, "answer": "hershey 's"}, {"question_id": 34614, "answer": "bud light"}, {"question_id": 34615, "answer": "$3.82"}, {"question_id": 34616, "answer": "yes"}, {"question_id": 34617, "answer": "red"}, {"question_id": 34618, "answer": "red label"}, {"question_id": 34619, "answer": "5"}, {"question_id": 34620, "answer": "3"}, {"question_id": 34621, "answer": "5"}, {"question_id": 34622, "answer": "yamaha"}, {"question_id": 34623, "answer": "2012"}, {"question_id": 34624, "answer": "macbook"}, {"question_id": 34625, "answer": "select your keyboard"}, {"question_id": 34626, "answer": "warning"}, {"question_id": 34627, "answer": "2010"}, {"question_id": 34628, "answer": "willis"}, {"question_id": 34629, "answer": "millrose games"}, {"question_id": 34630, "answer": "dumbledore"}, {"question_id": 34631, "answer": "king 's cross"}, {"question_id": 34632, "answer": "gioconda belli"}, {"question_id": 34633, "answer": "yes"}, {"question_id": 34634, "answer": "jeff vandermeer & mark roberts"}, {"question_id": 34635, "answer": "it is 1:53"}, {"question_id": 34636, "answer": "mediaczar"}, {"question_id": 34637, "answer": "your mom"}, {"question_id": 34638, "answer": "30"}, {"question_id": 34639, "answer": "jesus"}, {"question_id": 34640, "answer": "cloisters wetland"}, {"question_id": 34641, "answer": "57859"}, {"question_id": 34642, "answer": "57859"}, {"question_id": 34643, "answer": "yes"}, {"question_id": 34644, "answer": "50"}, {"question_id": 34645, "answer": "vodka"}, {"question_id": 34646, "answer": "chase"}, {"question_id": 34647, "answer": "honghe"}, {"question_id": 34648, "answer": "1 penny"}, {"question_id": 34649, "answer": "1 penny"}, {"question_id": 34650, "answer": "french"}, {"question_id": 34651, "answer": "california"}, {"question_id": 34652, "answer": "19:00 hs"}, {"question_id": 34653, "answer": "20"}, {"question_id": 34654, "answer": "tax"}, {"question_id": 34655, "answer": "9"}, {"question_id": 34656, "answer": "new york"}, {"question_id": 34657, "answer": "life cycle"}, {"question_id": 34658, "answer": "9"}, {"question_id": 34659, "answer": "ryman"}, {"question_id": 34660, "answer": "25 paise"}, {"question_id": 34661, "answer": "1985"}, {"question_id": 34662, "answer": "coronita extra"}, {"question_id": 34663, "answer": "coronita"}, {"question_id": 34664, "answer": "1855"}, {"question_id": 34665, "answer": "19"}, {"question_id": 34666, "answer": "white"}, {"question_id": 34667, "answer": "marvel"}, {"question_id": 34668, "answer": "1 and 2"}, {"question_id": 34669, "answer": "cocoa"}, {"question_id": 34670, "answer": "fry 's"}, {"question_id": 34671, "answer": "ray kurzweil"}, {"question_id": 34672, "answer": "postcode"}, {"question_id": 34673, "answer": "nls4 team"}, {"question_id": 34674, "answer": "wanita"}, {"question_id": 34675, "answer": "dewasa"}, {"question_id": 34676, "answer": "tua"}, {"question_id": 34677, "answer": "2012"}, {"question_id": 34678, "answer": "yes"}, {"question_id": 34679, "answer": "jiba"}, {"question_id": 34680, "answer": "9.0%"}, {"question_id": 34681, "answer": "smashed pumpkin"}, {"question_id": 34682, "answer": "coors light"}, {"question_id": 34683, "answer": "safeway"}, {"question_id": 34684, "answer": "cathy williams"}, {"question_id": 34685, "answer": "secrets of ruthless tycoon"}, {"question_id": 34686, "answer": "hot dog"}, {"question_id": 34687, "answer": "krainerwurst"}, {"question_id": 34688, "answer": "fox"}, {"question_id": 34689, "answer": "coca cola"}, {"question_id": 34690, "answer": "koala kare"}, {"question_id": 34691, "answer": "koala"}, {"question_id": 34692, "answer": "7:28"}, {"question_id": 34693, "answer": "ariel"}, {"question_id": 34694, "answer": "speaking eye"}, {"question_id": 34695, "answer": "southern homes"}, {"question_id": 34696, "answer": "648 home"}, {"question_id": 34697, "answer": "yamaha"}, {"question_id": 34698, "answer": "startling stories"}, {"question_id": 34699, "answer": "ward hawkins"}, {"question_id": 34700, "answer": "12:05"}, {"question_id": 34701, "answer": "budweiser"}, {"question_id": 34702, "answer": "016 399 5551"}, {"question_id": 34703, "answer": "yes"}, {"question_id": 34704, "answer": "kk dheeraj"}, {"question_id": 34705, "answer": "2011"}, {"question_id": 34706, "answer": "15:08:25"}, {"question_id": 34707, "answer": "juicy"}, {"question_id": 34708, "answer": "best cellars"}, {"question_id": 34709, "answer": "ipm"}, {"question_id": 34710, "answer": "gum plus"}, {"question_id": 34711, "answer": "gum plus"}, {"question_id": 34712, "answer": "yes"}, {"question_id": 34713, "answer": "clemson"}, {"question_id": 34714, "answer": "78"}, {"question_id": 34715, "answer": "dahit nimmt"}, {"question_id": 34716, "answer": "renaud camus"}, {"question_id": 34717, "answer": "revoltez vous"}, {"question_id": 34718, "answer": "holland"}, {"question_id": 34719, "answer": "matsuzakaya"}, {"question_id": 34720, "answer": "brahms klavierkonzert nr.1"}, {"question_id": 34721, "answer": "brahms"}, {"question_id": 34722, "answer": "mug"}, {"question_id": 34723, "answer": "star"}, {"question_id": 34724, "answer": "off"}, {"question_id": 34725, "answer": "on c"}, {"question_id": 34726, "answer": "blue star gallery 4"}, {"question_id": 34727, "answer": "soul doubt"}, {"question_id": 34728, "answer": "soon"}, {"question_id": 34729, "answer": "smoothies"}, {"question_id": 34730, "answer": "aj52 uyv"}, {"question_id": 34731, "answer": "ats"}, {"question_id": 34732, "answer": "ph sma"}, {"question_id": 34733, "answer": "ph sma"}, {"question_id": 34734, "answer": "blogs"}, {"question_id": 34735, "answer": "london undergroundblogspotcom"}, {"question_id": 34736, "answer": "yaam"}, {"question_id": 34737, "answer": "winter bar"}, {"question_id": 34738, "answer": "inspirations"}, {"question_id": 34739, "answer": "m\u043e\u0439 \u0434\u043e\u043c"}, {"question_id": 34740, "answer": "st george beer"}, {"question_id": 34741, "answer": "olivetti underwood"}, {"question_id": 34742, "answer": "joke shop"}, {"question_id": 34743, "answer": "halloween"}, {"question_id": 34744, "answer": "5:35 pm"}, {"question_id": 34745, "answer": "12"}, {"question_id": 34746, "answer": "pentagon channel"}, {"question_id": 34747, "answer": "army"}, {"question_id": 34748, "answer": "core values"}, {"question_id": 34749, "answer": "do you want to study in usa"}, {"question_id": 34750, "answer": "pulse width modulation"}, {"question_id": 34751, "answer": "pwm"}, {"question_id": 34752, "answer": "stahls"}, {"question_id": 34753, "answer": "39"}, {"question_id": 34754, "answer": "terrace hotel"}, {"question_id": 34755, "answer": "strand for stand"}, {"question_id": 34756, "answer": "portland"}, {"question_id": 34757, "answer": "tennessee"}, {"question_id": 34758, "answer": "live"}, {"question_id": 34759, "answer": "piano"}, {"question_id": 34760, "answer": "mike lee"}, {"question_id": 34761, "answer": "washington dc"}, {"question_id": 34762, "answer": "yes"}, {"question_id": 34763, "answer": "pringles stix"}, {"question_id": 34764, "answer": "umd"}, {"question_id": 34765, "answer": "yes"}, {"question_id": 34766, "answer": "roserbud"}, {"question_id": 34767, "answer": "5"}, {"question_id": 34768, "answer": "biohazard code: veronica"}, {"question_id": 34769, "answer": "jack of spades"}, {"question_id": 34770, "answer": "samsung"}, {"question_id": 34771, "answer": "color xpression"}, {"question_id": 34772, "answer": "stttgrt"}, {"question_id": 34773, "answer": "virginia"}, {"question_id": 34774, "answer": "redhook"}, {"question_id": 34775, "answer": "ale"}, {"question_id": 34776, "answer": "lancome"}, {"question_id": 34777, "answer": "dolce vita"}, {"question_id": 34778, "answer": "0"}, {"question_id": 34779, "answer": "pepsi"}, {"question_id": 34780, "answer": "adelsh"}, {"question_id": 34781, "answer": "geico"}, {"question_id": 34782, "answer": "390"}, {"question_id": 34783, "answer": "arsina"}, {"question_id": 34784, "answer": "second part"}, {"question_id": 34785, "answer": "pi"}, {"question_id": 34786, "answer": "tapiz"}, {"question_id": 34787, "answer": "malbec"}, {"question_id": 34788, "answer": "yes"}, {"question_id": 34789, "answer": "yes"}, {"question_id": 34790, "answer": "ian rankin"}, {"question_id": 34791, "answer": "memory in death"}, {"question_id": 34792, "answer": "12"}, {"question_id": 34793, "answer": "toshiba"}, {"question_id": 34794, "answer": "weganta"}, {"question_id": 34795, "answer": "ape lad"}, {"question_id": 34796, "answer": "canada"}, {"question_id": 34797, "answer": "w"}, {"question_id": 34798, "answer": "av 147 vz"}, {"question_id": 34799, "answer": "bar"}, {"question_id": 34800, "answer": "la grande blanche"}, {"question_id": 34801, "answer": "belgium"}, {"question_id": 34802, "answer": "baseball"}, {"question_id": 34803, "answer": "jr highway bus"}, {"question_id": 34804, "answer": "turkish airlines"}, {"question_id": 34805, "answer": "9350"}, {"question_id": 34806, "answer": "1:53"}, {"question_id": 34807, "answer": "vfw"}, {"question_id": 34808, "answer": "veterans of foreign wars"}, {"question_id": 34809, "answer": "same same"}, {"question_id": 34810, "answer": "flour"}, {"question_id": 34811, "answer": "video"}, {"question_id": 34812, "answer": "lenovo"}, {"question_id": 34813, "answer": "lenovo"}, {"question_id": 34814, "answer": "moritz"}, {"question_id": 34815, "answer": "barcelona"}, {"question_id": 34816, "answer": "schin"}, {"question_id": 34817, "answer": "lufthansa"}, {"question_id": 34818, "answer": "lufthansa"}, {"question_id": 34819, "answer": "10:24"}, {"question_id": 34820, "answer": ""}, {"question_id": 34821, "answer": "lg"}, {"question_id": 34822, "answer": "9:09"}, {"question_id": 34823, "answer": "uniqlo"}, {"question_id": 34824, "answer": "aldo"}, {"question_id": 34825, "answer": "packers"}, {"question_id": 34826, "answer": "packers"}, {"question_id": 34827, "answer": "nog 3 km nog 2 km nog 1 km"}, {"question_id": 34828, "answer": "3"}, {"question_id": 34829, "answer": "brick"}, {"question_id": 34830, "answer": "burnaby"}, {"question_id": 34831, "answer": "yes"}, {"question_id": 34832, "answer": "seals"}, {"question_id": 34833, "answer": "seals"}, {"question_id": 34834, "answer": "11:43"}, {"question_id": 34835, "answer": "10:25"}, {"question_id": 34836, "answer": "no"}, {"question_id": 34837, "answer": "fin"}, {"question_id": 34838, "answer": "29"}, {"question_id": 34839, "answer": "vodka"}, {"question_id": 34840, "answer": "007"}, {"question_id": 34841, "answer": "russia"}, {"question_id": 34842, "answer": "2"}, {"question_id": 34843, "answer": "5"}, {"question_id": 34844, "answer": "wine"}, {"question_id": 34845, "answer": "conde de toucauld"}, {"question_id": 34846, "answer": "1"}, {"question_id": 34847, "answer": "107"}, {"question_id": 34848, "answer": "west lothian"}, {"question_id": 34849, "answer": "59"}, {"question_id": 34850, "answer": "new york"}, {"question_id": 34851, "answer": "new york city"}, {"question_id": 34852, "answer": "master all malt"}, {"question_id": 34853, "answer": "2"}, {"question_id": 34854, "answer": "restoran el tercer ojito"}, {"question_id": 34855, "answer": "suntory"}, {"question_id": 34856, "answer": ""}, {"question_id": 34857, "answer": "ted"}, {"question_id": 34858, "answer": "june 28 2009"}, {"question_id": 34859, "answer": "rodda corona extra"}, {"question_id": 34860, "answer": "corona extra"}, {"question_id": 34861, "answer": "2l"}, {"question_id": 34862, "answer": "coca cola"}, {"question_id": 34863, "answer": "yes"}, {"question_id": 34864, "answer": "carnegie hall"}, {"question_id": 34865, "answer": "yes"}, {"question_id": 34866, "answer": "verizon"}, {"question_id": 34867, "answer": "yes"}, {"question_id": 34868, "answer": "kicker"}, {"question_id": 34869, "answer": "fox hd"}, {"question_id": 34870, "answer": "hd"}, {"question_id": 34871, "answer": "tanamera"}, {"question_id": 34872, "answer": "kimberly kay hoang"}, {"question_id": 34873, "answer": "dealing in desire"}, {"question_id": 34874, "answer": "silicon graphics"}, {"question_id": 34875, "answer": "17.3 inch"}, {"question_id": 34876, "answer": "1 oz"}, {"question_id": 34877, "answer": "not now"}, {"question_id": 34878, "answer": "ambr\u00e9e"}, {"question_id": 34879, "answer": "reynolds"}, {"question_id": 34880, "answer": "no minors"}, {"question_id": 34881, "answer": "office"}, {"question_id": 34882, "answer": "office"}, {"question_id": 34883, "answer": "motorola"}, {"question_id": 34884, "answer": "bitcoin"}, {"question_id": 34885, "answer": "psalm"}, {"question_id": 34886, "answer": "nortel networks"}, {"question_id": 34887, "answer": "game time budweiser"}, {"question_id": 34888, "answer": "portaria"}, {"question_id": 34889, "answer": "nokia"}, {"question_id": 34890, "answer": "ca ba"}, {"question_id": 34891, "answer": "1234567890"}, {"question_id": 34892, "answer": "s"}, {"question_id": 34893, "answer": "stop"}, {"question_id": 34894, "answer": "no"}, {"question_id": 34895, "answer": "english"}, {"question_id": 34896, "answer": "yes"}, {"question_id": 34897, "answer": "titanfall"}, {"question_id": 34898, "answer": "motorola"}, {"question_id": 34899, "answer": "natan"}, {"question_id": 34900, "answer": "10:10"}, {"question_id": 34901, "answer": "england"}, {"question_id": 34902, "answer": "basil"}, {"question_id": 34903, "answer": "yes"}, {"question_id": 34904, "answer": "boston tokyo"}, {"question_id": 34905, "answer": "only"}, {"question_id": 34906, "answer": "only"}, {"question_id": 34907, "answer": "stop"}, {"question_id": 34908, "answer": "p"}, {"question_id": 34909, "answer": "essential oil"}, {"question_id": 34910, "answer": "summer blend"}, {"question_id": 34911, "answer": "february 2012"}, {"question_id": 34912, "answer": "shiraz"}, {"question_id": 34913, "answer": "nature 's harvest"}, {"question_id": 34914, "answer": "macbook pro"}, {"question_id": 34915, "answer": "00:08:20 and 02:03:05"}, {"question_id": 34916, "answer": "squatting"}, {"question_id": 34917, "answer": "first"}, {"question_id": 34918, "answer": "hermes"}, {"question_id": 34919, "answer": "tab"}, {"question_id": 34920, "answer": "staples"}, {"question_id": 34921, "answer": "street army"}, {"question_id": 34922, "answer": "wladyslaw st reymont"}, {"question_id": 34923, "answer": "komediantka"}, {"question_id": 34924, "answer": "moon bar"}, {"question_id": 34925, "answer": "317"}, {"question_id": 34926, "answer": "30"}, {"question_id": 34927, "answer": "90"}, {"question_id": 34928, "answer": "extra virgin"}, {"question_id": 34929, "answer": "666"}, {"question_id": 34930, "answer": "anniversary ale"}, {"question_id": 34931, "answer": "anniversary ale"}, {"question_id": 34932, "answer": "2"}, {"question_id": 34933, "answer": "left"}, {"question_id": 34934, "answer": "right"}, {"question_id": 34935, "answer": "saggio"}, {"question_id": 34936, "answer": "francescantonio pescatore"}, {"question_id": 34937, "answer": "3"}, {"question_id": 34938, "answer": "chippewas"}, {"question_id": 34939, "answer": "allure"}, {"question_id": 34940, "answer": "sport"}, {"question_id": 34941, "answer": "2013"}, {"question_id": 34942, "answer": "2013"}, {"question_id": 34943, "answer": "1 million"}, {"question_id": 34944, "answer": "kane"}, {"question_id": 34945, "answer": "meijer"}, {"question_id": 34946, "answer": "8:52"}, {"question_id": 34947, "answer": "chargepoint"}, {"question_id": 34948, "answer": "hba"}, {"question_id": 34949, "answer": "slide:ology"}, {"question_id": 34950, "answer": "samsung"}, {"question_id": 34951, "answer": "skylar"}, {"question_id": 34952, "answer": "bud light"}, {"question_id": 34953, "answer": "new post"}, {"question_id": 34954, "answer": "w lawrence ave"}, {"question_id": 34955, "answer": "who"}, {"question_id": 34956, "answer": "5"}, {"question_id": 34957, "answer": "5"}, {"question_id": 34958, "answer": "648 3004"}, {"question_id": 34959, "answer": "green st"}, {"question_id": 34960, "answer": "10"}, {"question_id": 34961, "answer": "canon"}, {"question_id": 34962, "answer": "microsoft"}, {"question_id": 34963, "answer": "surface pro 3"}, {"question_id": 34964, "answer": "200ml"}, {"question_id": 34965, "answer": "no"}, {"question_id": 34966, "answer": "good for you"}, {"question_id": 34967, "answer": "adidas"}, {"question_id": 34968, "answer": "fff"}, {"question_id": 34969, "answer": "energy drink"}, {"question_id": 34970, "answer": "2"}, {"question_id": 34971, "answer": "no"}, {"question_id": 34972, "answer": "global warming"}, {"question_id": 34973, "answer": "stop global warming"}, {"question_id": 34974, "answer": "htc"}, {"question_id": 34975, "answer": "staten island"}, {"question_id": 34976, "answer": "ferry"}, {"question_id": 34977, "answer": "black"}, {"question_id": 34978, "answer": "monteith 's brewing co"}, {"question_id": 34979, "answer": "trig"}, {"question_id": 34980, "answer": "milt thomas"}, {"question_id": 34981, "answer": "cave of thousand tales"}, {"question_id": 34982, "answer": "rock stripes"}, {"question_id": 34983, "answer": "march"}, {"question_id": 34984, "answer": "neigh"}, {"question_id": 34985, "answer": "newcome"}, {"question_id": 34986, "answer": "malort"}, {"question_id": 34987, "answer": "926g"}, {"question_id": 34988, "answer": "no"}, {"question_id": 34989, "answer": "yes"}, {"question_id": 34990, "answer": "pinch"}, {"question_id": 34991, "answer": "yes"}, {"question_id": 34992, "answer": "1"}, {"question_id": 34993, "answer": "68.4"}, {"question_id": 34994, "answer": "12:04"}, {"question_id": 34995, "answer": "bottom right"}, {"question_id": 34996, "answer": "7 11"}, {"question_id": 34997, "answer": "113 aep 77"}, {"question_id": 34998, "answer": "yes"}, {"question_id": 34999, "answer": "whitecaps"}, {"question_id": 35000, "answer": "recycle"}, {"question_id": 35001, "answer": "macy 's"}, {"question_id": 35002, "answer": "macy 's"}, {"question_id": 35003, "answer": "1"}, {"question_id": 35004, "answer": "max"}, {"question_id": 35005, "answer": "2f85"}, {"question_id": 35006, "answer": "in"}, {"question_id": 35007, "answer": "5"}, {"question_id": 35008, "answer": "smart"}, {"question_id": 35009, "answer": "smart"}, {"question_id": 35010, "answer": "muffins"}, {"question_id": 35011, "answer": "angiucci cosmetti"}, {"question_id": 35012, "answer": "ontario"}, {"question_id": 35013, "answer": "member"}, {"question_id": 35014, "answer": "07 10 2012"}, {"question_id": 35015, "answer": "bentley university"}, {"question_id": 35016, "answer": "lenovo"}, {"question_id": 35017, "answer": "thinkpad"}, {"question_id": 35018, "answer": "13.0%"}, {"question_id": 35019, "answer": "new"}, {"question_id": 35020, "answer": "new"}, {"question_id": 35021, "answer": "jean paul sartre"}, {"question_id": 35022, "answer": "boston"}, {"question_id": 35023, "answer": "yes"}, {"question_id": 35024, "answer": "yes"}, {"question_id": 35025, "answer": "wood"}, {"question_id": 35026, "answer": "sheppy 's"}, {"question_id": 35027, "answer": "farmhouse cider"}, {"question_id": 35028, "answer": "3.50"}, {"question_id": 35029, "answer": "70"}, {"question_id": 35030, "answer": "mission"}, {"question_id": 35031, "answer": "drama and desire"}, {"question_id": 35032, "answer": "grappa nonino"}, {"question_id": 35033, "answer": "bella"}, {"question_id": 35034, "answer": "taco bell"}, {"question_id": 35035, "answer": "yes"}, {"question_id": 35036, "answer": "united states of america"}, {"question_id": 35037, "answer": "bus"}, {"question_id": 35038, "answer": "brugal"}, {"question_id": 35039, "answer": "brugal"}, {"question_id": 35040, "answer": "danger deep water"}, {"question_id": 35041, "answer": "deep water"}, {"question_id": 35042, "answer": "o"}, {"question_id": 35043, "answer": "1848coil"}, {"question_id": 35044, "answer": "beatles"}, {"question_id": 35045, "answer": "ludwig"}, {"question_id": 35046, "answer": "1794"}, {"question_id": 35047, "answer": "temper"}, {"question_id": 35048, "answer": "een"}, {"question_id": 35049, "answer": "yes"}, {"question_id": 35050, "answer": "f9"}, {"question_id": 35051, "answer": "google"}, {"question_id": 35052, "answer": "google"}, {"question_id": 35053, "answer": "china"}, {"question_id": 35054, "answer": "china"}, {"question_id": 35055, "answer": "dvr"}, {"question_id": 35056, "answer": "6.7%"}, {"question_id": 35057, "answer": "alternative transportation"}, {"question_id": 35058, "answer": "life"}, {"question_id": 35059, "answer": "26"}, {"question_id": 35060, "answer": "welcome to deep space diner"}, {"question_id": 35061, "answer": "deep space diner"}, {"question_id": 35062, "answer": "power monger"}, {"question_id": 35063, "answer": "start"}, {"question_id": 35064, "answer": "north shore watch and other poems"}, {"question_id": 35065, "answer": "12:30"}, {"question_id": 35066, "answer": "12:34 am"}, {"question_id": 35067, "answer": "fajita"}, {"question_id": 35068, "answer": "fajita revolution"}, {"question_id": 35069, "answer": "f6"}, {"question_id": 35070, "answer": "media cafe"}, {"question_id": 35071, "answer": "media cafe"}, {"question_id": 35072, "answer": "gender"}, {"question_id": 35073, "answer": "gentle"}, {"question_id": 35074, "answer": "fail"}, {"question_id": 35075, "answer": "pizza & subs"}, {"question_id": 35076, "answer": "big al 's"}, {"question_id": 35077, "answer": "dc shoes"}, {"question_id": 35078, "answer": "no"}, {"question_id": 35079, "answer": "5"}, {"question_id": 35080, "answer": "marjosse"}, {"question_id": 35081, "answer": "toto"}, {"question_id": 35082, "answer": "stop"}, {"question_id": 35083, "answer": "butter beats"}, {"question_id": 35084, "answer": "12:10"}, {"question_id": 35085, "answer": "3 mm"}, {"question_id": 35086, "answer": "18"}, {"question_id": 35087, "answer": "playstation 2"}, {"question_id": 35088, "answer": "rx"}, {"question_id": 35089, "answer": "texas"}, {"question_id": 35090, "answer": "t"}, {"question_id": 35091, "answer": "htc"}, {"question_id": 35092, "answer": "t"}, {"question_id": 35093, "answer": "spring outerwear"}, {"question_id": 35094, "answer": "google"}, {"question_id": 35095, "answer": "youtube"}, {"question_id": 35096, "answer": "margaret macmillan"}, {"question_id": 35097, "answer": "coco"}, {"question_id": 35098, "answer": "coco chanel"}, {"question_id": 35099, "answer": "qantas"}, {"question_id": 35100, "answer": "qantas"}, {"question_id": 35101, "answer": "10 20 30 40 50"}]